data/__init__.py
data/md_datamodule.py
data/qm_datamodule.py
data/components/__init__.py
data/components/datasets.py
data/components/graph.py
data/components/transformMD.py
data/components/transformQM.py
data/components/transforms.py
data/components/utils.py
misato_data/__init__.py
misato_data/md_datamodule.py
misato_data/qm_datamodule.py
misato_data/components/__init__.py
misato_data/components/datasets.py
misato_data/components/graph.py
misato_data/components/transformMD.py
misato_data/components/transformQM.py
misato_data/components/transforms.py
misato_data/components/utils.py
misato_data/processing/__init__.py
misato_data/processing/h5_to_pdb.py
misato_data/processing/inference_QM.py
misato_data/processing/pdb_to_h5.py
misato_data/processing/preprocessing_db.py
misato_dataset/__init__.py
misato_dataset/md_datamodule.py
misato_dataset/qm_datamodule.py
misato_dataset/components/__init__.py
misato_dataset/components/datasets.py
misato_dataset/components/graph.py
misato_dataset/components/transformMD.py
misato_dataset/components/transformQM.py
misato_dataset/components/transforms.py
misato_dataset/components/utils.py
misato_dataset/processing/__init__.py
misato_dataset/processing/h5_to_pdb.py
misato_dataset/processing/inference_QM.py
misato_dataset/processing/pdb_to_h5.py
misato_dataset/processing/preprocessing_db.py
misato_dataset-0.0.7.dist-info/LICENSE
misato_dataset-0.0.7.dist-info/METADATA
misato_dataset-0.0.7.dist-info/WHEEL
misato_dataset-0.0.7.dist-info/top_level.txt
misato_dataset-0.0.7.dist-info/RECORD
