Metadata-Version: 2.1
Name: misato-dataset
Version: 0.0.7
Summary: UNOFFICIAL Misato dataset pypi package. For instructions on dataset download see official GitHub page (https://github.com/t7morgen/misato-dataset).
Home-page: https://github.com/t7morgen/misato-dataset
Author: Jean Charle Yaacoub
Author-email: jyaacoub21@gmail.com
License: LGPL-2.1
Classifier: Programming Language :: Python :: 3.10
Classifier: License :: OSI Approved :: GNU Lesser General Public License v2 (LGPLv2)
Classifier: Operating System :: OS Independent
Requires-Python: >=3.10
License-File: LICENSE
Requires-Dist: matplotlib
Requires-Dist: h5py
Requires-Dist: pandas
Requires-Dist: numpy
Requires-Dist: torch
Requires-Dist: torch-geometric
Requires-Dist: torch-scatter
Requires-Dist: torch-sparse
Requires-Dist: pytorch-lightning
Requires-Dist: joblib
